[
  {
    "id": 1,
    "content": "Les prélèvements obligatoires\n\nURL: https://bip.cig929394.fr/fiches/remuneration-autres-avantages-financiers-cotisations/cotisations/cot\nSection: remuneration-autres-avantages-financiers-cotisations\nDate: 2026-03-04T22:39:22.821182\n\nContenu\n\nBarèmes pour l'évaluation forfaitaire de certains avantages en nature (AVANAT)\nLes cotisations au régime de retraite (COTISA)\nAccueil Fiches Rémunération, autres avantages financiers, cotisations Cotisations Les prélèvements obligatoires (COT)\nLes prélèvements obligatoires\nCOT\nI. CADRE GENERAL\nII. REGIME SPECIAL DE SECURITE SOCIALE\nIII. REGIME GENERAL DE SECURITE SOCIALE\nI. CADRE GENERAL\n1- Régime de sécurité sociale des agents publics territoriaux\nCette fiche présente les règles générales en matière de prélèvements obligatoires sur la rémunération des agents publics territoriaux. Ces derniers relèvent (-voir REGSPE) :\nsoit du régime spécial de sécurité sociale institué par le décret n°60-58 du 11 janvier 1960 (fonctionnaires titulaires et stagiaires affiliés à la CNRACL qui occupent un emploi à temps complet, ou un ou plusieurs emploi(s) à temps non complet mais pour une durée hebdomadaire de service au moins égale au seuil d'affiliation à la CNRACL)\nsoit du régime général de sécurité sociale (fonctionnaires titulaires et stagiaires qui occupent un ou plusieurs emploi(s) à temps non complet pour une durée hebdomadaire de service inférieure au seuil d'affiliation à la CNRACL, agents contractuels)\nL'appartenance à l'un ou l'autre de ces deux régimes a parfois une incidence sur la nature, l'assiette, le taux des prélèvements.\nIl faut noter que sont prévues, en plus de ces règles générales, des dispositions spécifiques à certaines catégories d'agents ou à certaines situations, notamment :\npour les sapeurs-pompiers professionnels\npour les agents qui occupent un emploi à temps non complet ou qui effectuent un service à temps partiel (-voir COTISA).\n2- Valeurs générales\n◈ Le plafond mensuel de la sécurité sociale est fixé, pour l'année 2026 à 4 005 euros (arr. min du 22 déc. 2025).\n◈ Avantages en nature : pour certains prélèvements, les avantages en nature font partie de l'assiette ; dans ce cas, ils doivent être évalués selon leur valeur représentative, qui est fixée par arrêté ministériel (art. R. 242-1 code de la sécurité sociale et arr. min. du 25 fév. 2025).\nPour connaître les montants applicables à compter du 1er janvier 2025, -voir AVANAT.\nLes modalités d'évaluation des avantages en nature, les règles applicables en matière de prélèvements ainsi que les obligations déclaratives incombant aux employeurs sont exposées dans une circulaire ministérielle du 1er juin 2007 (circ. min. du 1er juin 2007).\n◈ Frais professionnels : le montant des frais professionnels faisant l'objet d'un remboursement par l'employeur est déductible de l'assiette des cotisations sociales, dans les conditions et limites prévues par l'arr. min. du 4 sept. 2025, qui distingue deux régimes d'indemnisation des frais professionnels et d'exonération :\n→ le remboursement des frais réellement engagés par l'agent, sur présentation de justificatifs : les sommes versées sont intégralement déductibles de l'assiette des cotisations (ex : dépenses liées au télétravail, à l'utilisation des nouvelles technologies de l'information et de la communication) ;\n→ le remboursement sur la base d'allocations forfaitaires : les sommes versées font l'objet d'une exonération automatique dans la limite de montants plafonds. Dans le cas où les frais remboursés dépassent le montant plafond, ils sont déductibles de l'assiette si l'employeur est en mesure de prouver leur utilisation conforme pour la part excédant le plafond (ex : indemnités de mission, frais de déménagement, indemnité de panier).\n3- Autres prélèvements\nEn plus des différents prélèvements présentés ci-dessous, les employeurs publics territoriaux sont également assujettis :\n◈ A une cotisation obligatoire au CNFPT (-voir CENNAT) :\nLe taux de cette cotisation est voté par le conseil",
    "length": 3995
  },
  {
    "id": 2,
    "content": "d’administration du CNFPT, dans la limite d’un plafond fixé par la loi à 0,9% depuis le 1er janvier 2016.\nCette cotisation obligatoire est recouvrée et contrôlée par les URSSAF (art. L. 451-17 code général de la fonction publique, art. L. 451-18 code général de la fonction publique, art. L. 451-19 code général de la fonction publique et circ. min. du 26 déc. 2018).\n◈ A une cotisation obligatoire au centre de gestion, pour les collectivités et établissements affiliés (-voir CENGES)\nLe taux de cette cotisation est fixé par le conseil d'administration du CDG, dans la limite d’un plafond de 0,80% (art. L. 451-25 code général de la fonction publique et art. L. 451-28 code général de la fonction publique).\n◈ En cas d'adhésion au régime d'assurance-chômage, à une contribution de 4,05 % (4% à compter du 1er mai 2025) assise sur la rémunération de leurs agents contractuels et non statutaires ( (art. 50-1 règ. gén. du 15 nov. 2024 et -voir CHO).\nII. REGIME SPECIAL DE SECURITE SOCIALE\n◈ Cotisations au régime général de sécurité sociale (prestations en nature des assurances maladie, maternité et invalidité) :\nRÉFÉRENCE DE BASE ASSIETTE PART EMPLOYEUR PART AGENT\nart. 17 décr. n°60-58 du 11 janv. 1960 traitement indiciaire brut + NBI + complément de traitement indiciaire\n\n(art. 2 décr. n°67-850 du 30 sept. 1967 et\nart. 5 décr. n°93-863 du 18 juin 1993)\n9,88 %\n(art. 2 décr. n°67-850 du 30 sept. 1967)\n◈ Cotisations à la CNAF (allocations familiales) :\nRÉFÉRENCE DE BASE ASSIETTE PART EMPLOYEUR PART AGENT\nart. L. 241-6 code de la sécurité sociale\ntraitement indiciaire brut + NBI + complément de traitement indiciaire\n\n(art. 4 décr. n°95-38 du 6 janv. 1995 et\nart. D. 712-38 code de la sécurité sociale)\n5,25 %\n\n(art. D. 241-3-1 code de la sécurité sociale) -\n◈ Retenues et contributions à la CNRACL :\nRÉFÉRENCE DE BASE ASSIETTE PART EMPLOYEUR PART AGENT\nart. 3, I et II et art. 5 décr. n°2007-173 du 7 fév. 2007\ntraitement indiciaire brut + NBI + complément de traitement indiciaire\n(art. 3 I, I bis et II et art. 5 décr. n°2007-173 du 7 fév. 2007)\n37,65 %*\n\n(art. 5, II décr. n°91-613 du 28 juin 1991) 11,10 %\n\n(traitement indiciaire : art. 1er décr. n°2010-1749 du 30 déc. 2010\nNBI : art. 5, I, 4ème alinéa décr. n°91-613 du 28 juin 1991)\nà compter du 1er janvier 2026 ; le taux de la part employeur augmente chaque année jusqu'en 2028 (art. 5, II décr. n°91-613 du 28 juin 1991, -voir COTISA).\n◈ Cotisations au RAFP :\n(retraite additionnelle, -voir READDI)\nRÉFÉRENCE DE BASE ASSIETTE PART EMPLOYEUR PART AGENT\nart. 76 loi n°2003-775 du 21 août 2003\nIR + SFT + primes et indemnités + avantages en nature*\n\nplafond : l'assiette ne peut dépasser 20% du traitement indiciaire brut total perçu dans l'année\n\n(art. 2 décr. n°2004-569 du 18 juin 2004)\n5 %\n(art. 3 décr. n°2004-569 du 18 juin 2004)\n5 %\n(art. 3 décr. n°2004-569 du 18 juin 2004)\nà noter : la participation de l'employeur public au financement d'un contrat collectif de protection sociale complémentaire auquel la souscription des agents est rendue obligatoire en application d'un accord est exclue de cette assiette (application rétroactive au 1er janvier 2022) (art. 76 loi n°2003-775 du 21 août 2003 et -voir PARTIC).\n◈ Réduction des cotisations « agent » versées au régime de retraite au titre des heures supplémentaires :\nA compter du 1er janvier 2019, une réduction des cotisations (part agent) versées au régime de retraite est appliquée aux cotisations dues au titre des heures supplémentaires (art. L. 241-17 code de la sécurité sociale et décr. n°2019-133 du 25 fév. 2019), se reporter à la fiche REHSUP.\n◈ CSG :\nRÉFÉRENCE DE BASE ASSIETTE PART EMPLOYEUR PART AGENT\nart. L. 136-1 code de la sécurité sociale\nart. L. 136-1-1 code de la sécurité sociale\nart. L. 136-1-2 code de la sécurité sociale\n98,25 % du montant brut total des rémunérations, avantages en nature*\n(art. L. 136-2 code de la sécurité sociale)\n9,20 % (2,40 % soumis à l'impôt sur le revenu + 6,80 % déductibles)\n(art. L. 136-8 code de la sécurité",
    "length": 3991
  },
  {
    "id": 3,
    "content": "sociale)\nLorsque la rémunération est au moins égale à quatre fois le plafond de la sécurité sociale, soit 16 020 euros/mois, elle est assujettie à la CSG, à partir du 16 020ème euro, pour 100% de son montant\n◈ CRDS :\nRÉFÉRENCE DE BASE ASSIETTE PART EMPLOYEUR PART AGENT\nart. 14 I ord. n°96-50 du 24 janv. 1996\ncirc. min. du 2 fév. 1996\n98,25 % du montant brut total des rémunérations, avantages en nature*\n(art. 14, I ord. n°96-50 du 24 janv. 1996 et\nart. L. 136-2 code de la sécurité sociale)\n0,50 % (soumis à l'impôt sur le revenu)\n(art. 19 ord. n°96-50 du 24 janv. 1996)\nLorsque la rémunération est au moins égale à quatre fois le plafond de la sécurité sociale, soit 16 020 euros/mois, elle est assujettie à la CRDS, à partir du 16 020ème euro, pour 100% de son montant\n◈ Contribution de solidarité autonomie :\nRÉFÉRENCE DE BASE ASSIETTE PART EMPLOYEUR PART AGENT\nart. L. 137-40 code de la sécurité sociale\ntraitement indiciaire brut + NBI + complément de traitement indiciaire\n(art. L. 137-40 code de la sécurité sociale)\n0,30 %\n(art. L. 137-40 code de la sécurité sociale)\n◈ Cotisations au titre de l'allocation temporaire d'invalidité (ATIACL) :\nRÉFÉRENCE DE BASE ASSIETTE PART EMPLOYEUR PART AGENT\nart. 16 décr. n°2005-442 du 2 mai 2005\ntraitement indiciaire brut*\n(art. 16 décr. n°2005-442 du 2 mai 2005 et\ncirc. min. du 15 mars 1993)\n0,40 %\narr. min. du 28 déc. 2012\nà noter : la NBI et le complément de traitement indiciaires sont exclus de l'assiette (source : CNRACL)\n◈ Cotisation et contribution au Fonds national d'aide au logement (FNAL) :\nRÉFÉRENCE DE BASE ASSIETTE PART EMPLOYEUR PART AGENT\nart. L. 834-1 code de la sécurité sociale\ntraitement indiciaire brut + NBI + complément de traitement indiciaire\n(art. R. 834-7 code de la sécurité sociale)\ncollectivités employant au moins 50 agents : 0,50 %\n\ncollectivités employant moins de 50 agents : 0,10 % sur l'assiette limitée au plafond de la sécurité sociale, soit 4 005 euros pour 2026\n\n(art. L. 834-1 code de la sécurité sociale)\n◈ Versement mobilité et versement mobilité régional :\nCONDITIONS D'ASSUJETTISSEMENT ASSIETTE PART EMPLOYEUR PART AGENT\nVersement mobilité :\nIle-de-France : obligatoire par les collectivités employant au moins 11 agents\nart. L. 2531-2 code général des collectivités territoriales\nProvince : collectivités employant au moins 11 agents dans une zone où a été institué un tel versement (par délibération du conseil municipal ou de l'organe compétent de l'établissement public qui organise un service de transport public)\nart. L. 2333-64 code général des collectivités territoriales et\nart. L. 2333-66 code général des collectivités territoriales\ntraitement indiciaire brut + NBI + complément de traitement indiciaire\n(art. L. 2531-3 code général des collectivités territoriales et\nart. L. 2333-65 code général des collectivités territoriales)\nIle de France :\nParis et départements des Hauts-de-Seine, de la Seine-Saint-Denis et du Val-de-Marne : 3,20 %* à compter du 1er février 2024\nAutres départements :\n→ dans les communes listées à l'art. R. 2531-6 code général des collectivités territoriales : 2,01 %\n→ dans les autres communes : 1,60 %\n(art. L. 2531-4 code général des collectivités territoriales et\nart. R. 2531-6 code général des collectivités territoriales)\nProvince : variable\n(art. L. 2333-67 code général des collectivités territoriales)\nVersement mobilité régional :\nIle-de-France : non applicable\nProvince : collectivités employant au moins 11 agents dans une zone où une délibération du conseil régional ou de l’organe délibérant de la collectivité de Corse a institué un tel versement\nart. L. 4332-8-1 code général des collectivités territoriales et\nart. L. 2333-64 code général des collectivités territoriales\ntraitement indiciaire brut + NBI + complément de traitement indiciaire\n(art. L. 4332-8-1 code général des collectivités territoriales et\nart. L. 2333-65 code général des collectivités territoriales)\nvariable, dans la limite de 0,15 %\n(art. L. 4332-8-1 code général des",
    "length": 3993
  },
  {
    "id": 4,
    "content": "collectivités territoriales)\nTaux fixé par délibération du conseil d'administration d'Ile-de France Mobilités dans les limites indiquées dans ce tableau ; toute modification de taux entre en vigueur au 1er janvier ou au 1er juillet de chaque année après délibération du syndicat des transports \"Ile-de France Mobilités\" (art. L. 2531-4 code général des collectivités territoriales) ; par dérogation, l'augmentation du taux de 2,95% à 3,20 % s'applique à compter du 1er février 2024 (délibération d’Île-de-France Mobilités du 30 décembre 2023).\nIII. REGIME GENERAL DE SECURITE SOCIALE\n◈ Cotisations au titre des assurances maladie, maternité, invalidité et décès :\nRÉFÉRENCE DE BASE ASSIETTE PART EMPLOYEUR PART AGENT\nart. L. 242-1 code de la sécurité sociale montant brut total des rémunérations et avantages en nature\n\n(art. L. 242-1 code de la sécurité sociale)\n13 %\n(art. D. 242-3 code de la sécurité sociale)\n◈ Cotisation au titre du régime local d'assurance maladie complémentaire obligatoire dans les départements du Haut-Rhin, du Bas-Rhin et de la Moselle :\nRÉFÉRENCE DE BASE ASSIETTE PART EMPLOYEUR PART AGENT\nart. L. 242-13 code de la sécurité sociale\nmontant brut total des rémunérations et avantages en nature\n(art. L. 242-13 code de la sécurité sociale)\n1,30 %*\n(art. D. 325-4 code de la sécurité sociale, 5°)\nDécision du conseil d'administration de l'instance de gestion du régime local du 16 décembre 2021\n◈ Cotisations au titre des accidents du travail et des maladies professionnelles :\nRÉFÉRENCE DE BASE ASSIETTE PART EMPLOYEUR PART AGENT\nart. L. 241-5 code de la sécurité sociale\nmontant brut total des rémunérations et avantages en nature\n(art. L. 242-1 code de la sécurité sociale)\nTaux collectifs :\ncollectivités territoriales y compris leurs établissements publics hors secteur médico-social : 1,66 %*\nétablissements publics médico-sociaux des collectivités territoriales : 1,30 %*\nTaux spécifiques aux départements du Haut-Rhin, du Bas-Rhin et de la Moselle :\ncollectivités territoriales y compris leurs établissements publics hors secteur médico-social : 1,31 %*\nétablissements publics médico-sociaux des collectivités territoriales : 2,35 %*\n(art. L. 242-5 code de la sécurité sociale ; art. D. 242-6-11 code de la sécurité sociale\ndécr. n°2025-318 du 4 avr. 2025\narr. min. du 17 oct. 1995\narr. min. du 30 déc. 2025)\nTaux à compter du 1er janvier 2026 (arr. min. du 30 déc. 2025)\n◈ Cotisations à la CNAF (allocations familiales) :\nRÉFÉRENCE DE BASE ASSIETTE PART EMPLOYEUR PART AGENT\nart. L. 241-6 code de la sécurité sociale\nmontant brut total des rémunérations et avantages en nature\n\n(art. L. 242-1 code de la sécurité sociale)\n5,25%\n\n(art. D. 241-3-1 code de la sécurité sociale) -\n◈ Cotisations au titre de l'assurance vieillesse :\nRÉFÉRENCE DE BASE ASSIETTE PART EMPLOYEUR PART AGENT\nart. L. 241-3 code de la sécurité sociale\nmontant brut total des rémunérations et avantages en nature\n\n(art. L. 242-1 code de la sécurité sociale)\n2,11 %* sur la totalité de l'assiette\n8,55 % sur la part de l'assiette qui ne dépasse pas le plafond de la sécurité sociale (4 005 euros mensuels pour 2026)\n(art. D. 242-4 code de la sécurité sociale)\n0,40 % sur la totalité de l'assiette\n6,90 % sur la part de l'assiette qui ne dépasse pas le plafond de la sécurité sociale (4 005 euros mensuels pour 2026)\n(art. D. 242-4 code de la sécurité sociale)\nTaux à compter du 1er janvier 2026.\n◈ Cotisations à l'IRCANTEC :\nRÉFÉRENCE DE BASE ASSIETTE PART EMPLOYEUR PART AGENT\nart. 7 décr. n°70-1277 du 23 déc. 1970\nmontant brut total des rémunérations et avantages en nature, à l'exclusion des éléments à caractère familial, des indemnités représentatives de frais et des prestations familiales\n\n(art. 7 décr. n°70-1277 du 23 déc. 1970)\ntaux sur la tranche A (tranche de l'assiette inférieure ou égale au plafond de la sécurité sociale, soit 4 005 euros pour 2026) : 4,27 %*\ntaux sur la tranche B (tranche de l'assiette supérieure au plafond et ne dépassant pas 8 fois son montant, soit entre 4",
    "length": 3999
  },
  {
    "id": 5,
    "content": "005 euros et 32 040 euros pour 2026) : 12,75 %*\n(arr. min. du 14 janv. 1971)\ntaux sur la tranche A (tranche de l'assiette inférieure ou égale au plafond de la sécurité sociale, soit 4 005 euros pour 2026) : 2,84 %*\ntaux sur la tranche B (tranche de l'assiette supérieure au plafond et ne dépassant pas 8 fois son montant, soit entre 4 005 euros et 32 040 euros pour 2026) : 7,06 %* pour la part agent\n(arr. min. du 14 janv. 1971)\nTaux à compter du 1er janvier 2026 (source : Ircantec).\n◈ Réduction des cotisations « agent » versées au régime d’assurance vieillesse au titre des heures supplémentaires :\nA compter du 1er janvier 2019, une réduction des cotisations (part agent) versées au régime d’assurance vieillesse est appliquée aux cotisations dues au titre des heures supplémentaires (art. L. 241-17 code de la sécurité sociale et décr. n°2019-133 du 25 fév. 2019).\nPour plus de détails, -voir REHSUP.\n◈ CSG :\nRÉFÉRENCE DE BASE ASSIETTE PART EMPLOYEUR PART AGENT\nart. L. 136-1 code de la sécurité sociale\nart. L. 136-1-1 code de la sécurité sociale\nart. L. 136-1-2 code de la sécurité sociale\n98,25 % du montant brut total des rémunérations, avantages en nature*\n(art. L. 136-2 code de la sécurité sociale)\n9,20 % (2,40 % soumis à l'impôt sur le revenu + 6,80 % déductibles\n(art. L. 136-8 code de la sécurité sociale)\nLorsque la rémunération est au moins égale à quatre fois le plafond de la sécurité sociale, soit 16 020 euros/mois, elle est assujettie à la CSG, à partir du 16 020ème euro, pour 100% de son montant\n◈ CRDS :\nRÉFÉRENCE DE BASE ASSIETTE PART EMPLOYEUR PART AGENT\nart. 14 I ord. n°96-50 du 24 janv. 1996\ncirc. min. du 2 fév. 1996\n98,25 % du montant brut total des rémunérations, avantages en nature*\n(art. 14 I ord. n°96-50 du 24 janv. 1996 et\nart. L. 136-2 code de la sécurité sociale)\n0,50 % (soumis à l'impôt sur le revenu)\n(art. 19 ord. n°96-50 du 24 janv. 1996)\nLorsque la rémunération est au moins égale à quatre fois le plafond de la sécurité sociale, soit 16 020 euros/mois, elle est assujettie à la CRDS, à partir du 16 020ème euro, pour 100% de son montant\n◈ Contribution de solidarité autonomie :\nRÉFÉRENCE DE BASE ASSIETTE PART EMPLOYEUR PART AGENT\nart. L. 137-40 code de la sécurité sociale\nmontant brut total des rémunérations et avantages en nature\n(art. L. 137-40 code de la sécurité sociale)\n0,30 %\n(art. L. 137-40 code de la sécurité sociale)\n◈ Cotisation et contribution au Fonds national d'aide au logement (FNAL) :\nRÉFÉRENCE DE BASE ASSIETTE PART EMPLOYEUR PART AGENT\nart. L. 834-1 code de la sécurité sociale\nmontant brut total des rémunérations, avantages en nature\n(art. R. 834-7 code de la sécurité sociale)\ncollectivités employant au moins 50 agents : 0,50 %\n\ncollectivités employant moins de 50 agents : 0,10 % sur l'assiette limitée au plafond de la sécurité sociale, soit 4 005 euros pour 2026\n\n(art. L. 834-1 code de la sécurité sociale)\n◈ Versement mobilité et versement mobilité régional :\nCONDITIONS D'ASSUJETTISSEMENT ASSIETTE PART EMPLOYEUR PART AGENT\nVersement mobilité :\nIle-de-France : obligatoire par les collectivités employant au moins 11 agents\nart. L. 2531-2 code général des collectivités territoriales\nProvince : collectivités employant au moins 11 agents dans une zone où a été institué un tel versement (par délibération du conseil municipal ou de l'organe compétent de l'établissement public qui organise un service de transport public)\nart. L. 2333-64 code général des collectivités territoriales et\nart. L. 2333-66 code général des collectivités territoriales\nmontant brut total des rémunérations et avantages en nature\n(art. L. 2531-3 code général des collectivités territoriales et\nart. L. 2333-65 code général des collectivités territoriales)\nIle de France :\nParis et départements des Hauts-de-Seine, de la Seine-Saint-Denis et du Val-de-Marne : 3,20 %* à compter du 1er février 2024\nAutres départements :\n→ dans les communes listées à l'art. R. 2531-6 code général des collectivités territoriales : 2,01%\n→ dans les autres",
    "length": 3996
  },
  {
    "id": 6,
    "content": "communes : 1,60 %\n(art. L. 2531-4 code général des collectivités territoriales et\nart. R. 2531-6 code général des collectivités territoriales)\nProvince : variable\n(art. L. 2333-67 code général des collectivités territoriales)\nVersement mobilité régional :\nIle-de-France : non applicable\nProvince : collectivités employant au moins 11 agents dans une zone où une délibération du conseil régional ou de l’organe délibérant de la collectivité de Corse a institué un tel versement\nart. L. 4332-8-1 code général des collectivités territoriales et\nart. L. 2333-64 code général des collectivités territoriales\nmontant brut total des rémunérations et avantages en nature\n(art. L. 4332-8-1 code général des collectivités territoriales et\nart. L. 2333-65 code général des collectivités territoriales)\nvariable, dans la limite de 0,15 %\n(art. L. 4332-8-1 code général des collectivités territoriales)\nTaux fixé par délibération du conseil d'administration d'Ile-de France Mobilités dans les limites indiquées dans ce tableau ; toute modification de taux entre en vigueur au 1er janvier ou au 1er juillet de chaque année après délibération du syndicat des transports \"Ile-de France Mobilités\" (art. L. 2531-4 code général des collectivités territoriales) ; par dérogation, l'augmentation du taux de 2,95% à 3,20 % s'applique à compter du 1er février 2024 (délibération d’Île-de-France Mobilités du 30 décembre 2023).\nFiches en référence\n\nTextes en référence",
    "length": 1445
  }
]
